warise_first/__init__.py
warise_first/__main__.py
warise_first/example.py
warise_first-0.0.25.dist-info/LICENSE
warise_first-0.0.25.dist-info/METADATA
warise_first-0.0.25.dist-info/WHEEL
warise_first-0.0.25.dist-info/top_level.txt
warise_first-0.0.25.dist-info/RECORD
