Metadata-Version: 2.1
Name: warise-first
Version: 0.0.25
Summary: A small warise package
Author-email: warise <warise0523@gmail.com>
Project-URL: Homepage, https://github.com/kenno-warise/wariseproject
Project-URL: Bug Tracker, https://github.com/kenno-warise/wariseproject/issues
Classifier: Programming Language :: Python :: 3
Classifier: License :: OSI Approved :: MIT License
Classifier: Operating System :: OS Independent
Requires-Python: >=3.7
License-File: LICENSE
Requires-Dist: bs4 (==0.0.1)
Requires-Dist: requests (>=2.28.2)
